get_data_7_25/main.py
get_data_7_25/api/__init__.py
get_data_7_25/api/get_api.py
get_data_7_25/book/get_book.py
get_data_7_25/book/bunko/get_bunko.py
get_data_7_25/book/tankoubon/get_tankoubon.py
get_data_7_25-0.1.8.dist-info/LICENSE
get_data_7_25-0.1.8.dist-info/METADATA
get_data_7_25-0.1.8.dist-info/WHEEL
get_data_7_25-0.1.8.dist-info/entry_points.txt
get_data_7_25-0.1.8.dist-info/top_level.txt
get_data_7_25-0.1.8.dist-info/RECORD
